dcs_wrapper/__init__.py
dcs_wrapper/base.py
dcs_wrapper/tags.py
dcs_wrapper/utils.py
dcs_wrapper/wrapper.py
dcs_wrapper/data/dcs_data.tar.gz
dcs_wrapper-0.0.1.dist-info/DESCRIPTION.rst
dcs_wrapper-0.0.1.dist-info/METADATA
dcs_wrapper-0.0.1.dist-info/RECORD
dcs_wrapper-0.0.1.dist-info/WHEEL
dcs_wrapper-0.0.1.dist-info/metadata.json
dcs_wrapper-0.0.1.dist-info/top_level.txt
