Metadata-Version: 2.0
Name: dcs-wrapper
Version: 0.0.1
Summary: Wrapper around Digital Corpus of Sanskrit
Home-page: https://github.com/avinashvarna/dcs_wrapper
Author: Sanskrit programmers
Author-email: sanskrit-programmers@googlegroups.com
License: MIT
Keywords: sanskrit samskritam database corpus
Platform: UNKNOWN
Classifier: Development Status :: 3 - Alpha
Classifier: Intended Audience :: Education
Classifier: Intended Audience :: Science/Research
Classifier: Intended Audience :: Developers
Classifier: Topic :: Text Processing :: Linguistic
Classifier: License :: OSI Approved :: MIT License
Classifier: Programming Language :: Python :: 2
Classifier: Programming Language :: Python :: 2.7
Classifier: Programming Language :: Python :: 3
Classifier: Programming Language :: Python :: 3.6
Requires-Dist: indic-transliteration
Requires-Dist: six
Requires-Dist: backports.functools-partialmethod
Requires-Dist: backports.functools-lru-cache
